RattletrapPython/__init__.py
RattletrapPython/rattletrap.exe
RattletrapPython/rattletrap.py
RattletrapPython/version.py
RattletrapPython-9.0.6.5.data/data/rattletrap.exe
RattletrapPython-9.0.6.5.dist-info/METADATA
RattletrapPython-9.0.6.5.dist-info/WHEEL
RattletrapPython-9.0.6.5.dist-info/top_level.txt
RattletrapPython-9.0.6.5.dist-info/RECORD
